vibesort/__init__.py
vibesort/ai.py
vibesort/py.typed
vibesort-0.1.1.dist-info/METADATA
vibesort-0.1.1.dist-info/WHEEL
vibesort-0.1.1.dist-info/licenses/LICENSE
vibesort-0.1.1.dist-info/RECORD
