Metadata-Version: 2.4
Name: vibesort
Version: 0.1.1
Summary: Sorting library that uses GPT to sort arrays
Author-email: Aziz Berkay Yesilyurt <abyesilyurt@gmail.com>
License-File: LICENSE
Requires-Python: >=3.10
Requires-Dist: openai>=1.95.1
Requires-Dist: pydantic>=2.11.7
Requires-Dist: typing-extensions>=4.14.1
